qanary_helpers/__init__.py
qanary_helpers/language_queries.py
qanary_helpers/qanary_queries.py
qanary_helpers/registration.py
qanary_helpers/registrator.py
qanary_helpers/logging/__init__.py
qanary_helpers/logging/component_logging.py
qanary_helpers/logging/config.py
qanary_helpers/logging/get_ssh_key.py
tests/__init__.py
tests/test_logging.py
tests/test_qanary_queries.py
tests/test_registration.py
tests/test_registrator.py
qanary_helpers-0.3.2.dist-info/LICENSE
qanary_helpers-0.3.2.dist-info/METADATA
qanary_helpers-0.3.2.dist-info/WHEEL
qanary_helpers-0.3.2.dist-info/top_level.txt
qanary_helpers-0.3.2.dist-info/RECORD
