Metadata-Version: 2.1
Name: qanary-helpers
Version: 0.3.2
Summary: A package that helps to build Python components for the Qanary Question Answering framework
Home-page: https://github.com/WSE-research/qanary_helpers
Author: Andreas Both, Aleksandr Perevalov
Author-email: andreas.both@htwk-leipzig.de, aleksandr.perevalov@htwk-leipzig.de
License: UNKNOWN
Platform: UNKNOWN
Classifier: Programming Language :: Python
Classifier: Programming Language :: Python :: 3
Classifier: Programming Language :: Python :: 3.7
Classifier: Programming Language :: Python :: 3.8
Classifier: Programming Language :: Python :: 3.9
Classifier: License :: OSI Approved :: MIT License
Classifier: Operating System :: OS Independent
Requires-Python: >=3.7
Requires-Dist: SPARQLWrapper
Requires-Dist: flask
Requires-Dist: mlflow
Requires-Dist: pysftp
Requires-Dist: requests
Requires-Dist: setuptools
